text_gists/__init__.py
text_gists/__main__.py
text_gists/constructors.py
text_gists-0.0.2.dist-info/WHEEL
text_gists-0.0.2.dist-info/METADATA
text_gists-0.0.2.dist-info/RECORD
