Metadata-Version: 2.1
Name: text-gists
Version: 0.0.2
Summary: Helper functions for matching regex and other text-based patterns.
Author: Marcelino G. Veloso III
Author-email: mars@veloso.one
Requires-Python: >=3.10,<4.0
Classifier: Programming Language :: Python :: 3
Classifier: Programming Language :: Python :: 3.10
Classifier: Programming Language :: Python :: 3.11
